vgis_rs/__init__.py
vgis_rs/rsTools.py
vgis_rs/tifTools.py
vgis_rs-1.1.9.dist-info/METADATA
vgis_rs-1.1.9.dist-info/WHEEL
vgis_rs-1.1.9.dist-info/top_level.txt
vgis_rs-1.1.9.dist-info/RECORD
