Metadata-Version: 2.1
Name: vgis_rs
Version: 1.1.9
Summary: A libary for rs operator
Home-page: https://github.com/gisfanmachel/vgisRs
Author: gisfanmachel
Author-email: gisfanmachel@gmail.com
Keywords: rs,setuptools,development
Classifier: Development Status :: 3 - Alpha
Classifier: Intended Audience :: Developers
Classifier: Topic :: Software Development :: Build Tools
Classifier: License :: OSI Approved :: MIT License
Classifier: Programming Language :: Python :: 3
Classifier: Programming Language :: Python :: 3.7
Classifier: Programming Language :: Python :: 3.8
Classifier: Programming Language :: Python :: 3.9
Classifier: Programming Language :: Python :: 3.10
Classifier: Programming Language :: Python :: 3 :: Only
Requires-Python: >=3.7, <4
Requires-Dist: opencv-python
Requires-Dist: Pillow
Requires-Dist: vgis_gis
